
{"items":[{"name":"ranges","href":"ranges.html","topicHref":"ranges.html"},{"name":"stoppingPolicy","href":"stoppingPolicy.html","topicHref":"stoppingPolicy.html"},{"name":"lockstepMixinFF","href":"lockstepMixinFF.html","topicHref":"lockstepMixinFF.html"},{"name":"lockstepMixinTF","href":"lockstepMixinTF.html","topicHref":"lockstepMixinTF.html"},{"name":"lockstepMixinFT","href":"lockstepMixinFT.html","topicHref":"lockstepMixinFT.html"},{"name":"lockstepMixinTT","href":"lockstepMixinTT.html","topicHref":"lockstepMixinTT.html"}],"pdf":false}
