
{"order":100,"items":[{"name":"sharLowerBound","href":"sharLowerBound.html","topicHref":"sharLowerBound.html"},{"name":"sharSwitchLowerBound","href":"sharSwitchLowerBound.html","topicHref":"sharSwitchLowerBound.html"},{"name":"_RealArray","href":"_RealArray.html","topicHref":"_RealArray.html"},{"name":"CodepointSet","href":"CodepointSet.html","topicHref":"CodepointSet.html"},{"name":"lo8","href":"lo8.html","topicHref":"lo8.html"},{"name":"mlo8","href":"mlo8.html","topicHref":"mlo8.html"},{"name":"PackedArrayView","href":"PackedArrayView.html","topicHref":"PackedArrayView.html"},{"name":"PackedPtr","href":"PackedPtr.html","topicHref":"PackedPtr.html"},{"name":"Prefix","href":"Prefix.html","topicHref":"Prefix.html"},{"name":"CodepointSetTrie","href":"CodepointSetTrie.html","topicHref":"CodepointSetTrie.html"},{"name":"Prefix","href":"Prefix.html","topicHref":"Prefix.html"},{"name":"CodepointTrie","href":"CodepointTrie.html","topicHref":"CodepointTrie.html"},{"name":"Prefix","href":"Prefix.html","topicHref":"Prefix.html"},{"name":"getIndex","href":"getIndex.html","topicHref":"getIndex.html"},{"name":"useItemAt","href":"useItemAt.html","topicHref":"useItemAt.html"},{"name":"useLastItem","href":"useLastItem.html","topicHref":"useLastItem.html"}],"pdf":false}
