
{"order":100,"items":[{"name":"Overview","href":"Overview.html","topicHref":"Overview.html"},{"name":"Structs","includedFrom":"~/phobos/std/regex/internal/parser/Structs/toc.yml","items":[{"name":"CodeGen","href":"Structs/CodeGen.html","topicHref":"Structs/CodeGen.html"},{"name":"Parser","href":"Structs/Parser.html","topicHref":"Structs/Parser.html"}]},{"name":"Functions","includedFrom":"~/phobos/std/regex/internal/parser/Functions/toc.yml","items":[{"name":"makeRegex","href":"Functions/makeRegex.html","topicHref":"Functions/makeRegex.html"},{"name":"reverseBytecode","href":"Functions/reverseBytecode.html","topicHref":"Functions/reverseBytecode.html"},{"name":"postprocess","href":"Functions/postprocess.html","topicHref":"Functions/postprocess.html"},{"name":"fixupBytecode","href":"Functions/fixupBytecode.html","topicHref":"Functions/fixupBytecode.html"},{"name":"optimize","href":"Functions/optimize.html","topicHref":"Functions/optimize.html"},{"name":"validateRe","href":"Functions/validateRe.html","topicHref":"Functions/validateRe.html"}]}],"pdf":false}
