
{"items":[{"name":"SOCKET","href":"SOCKET.html","topicHref":"SOCKET.html"},{"name":"IP","href":"IP.html","topicHref":"IP.html"},{"name":"ICMP","href":"ICMP.html","topicHref":"ICMP.html"},{"name":"IGMP","href":"IGMP.html","topicHref":"IGMP.html"},{"name":"GGP","href":"GGP.html","topicHref":"GGP.html"},{"name":"TCP","href":"TCP.html","topicHref":"TCP.html"},{"name":"PUP","href":"PUP.html","topicHref":"PUP.html"},{"name":"UDP","href":"UDP.html","topicHref":"UDP.html"},{"name":"IDP","href":"IDP.html","topicHref":"IDP.html"},{"name":"RAW","href":"RAW.html","topicHref":"RAW.html"},{"name":"IPV6","href":"IPV6.html","topicHref":"IPV6.html"}],"pdf":false}
