
{"items":[{"name":"remove","href":"remove.html","topicHref":"remove.html"},{"name":"findAndRemove","href":"findAndRemove.html","topicHref":"findAndRemove.html"},{"name":"dump","href":"dump.html","topicHref":"dump.html"},{"name":"formatSizes","href":"formatSizes.html","topicHref":"formatSizes.html"},{"name":"rotate","href":"rotate.html","topicHref":"rotate.html"},{"name":"insertAsRoot","href":"insertAsRoot.html","topicHref":"insertAsRoot.html"},{"name":"assertValid","href":"assertValid.html","topicHref":"assertValid.html"},{"name":"goodAllocSize","href":"goodAllocSize.html","topicHref":"goodAllocSize.html"},{"name":"allocate","href":"allocate.html","topicHref":"allocate.html"},{"name":"deallocate","href":"deallocate.html","topicHref":"deallocate.html"},{"name":"clear","href":"clear.html","topicHref":"clear.html"},{"name":"deallocateAll","href":"deallocateAll.html","topicHref":"deallocateAll.html"}],"pdf":false}
