
{"items":[{"name":"pre","href":"pre.html","topicHref":"pre.html"},{"name":"post","href":"post.html","topicHref":"post.html"},{"name":"hit","href":"hit.html","topicHref":"hit.html"},{"name":"front","href":"front.html","topicHref":"front.html"},{"name":"popFront","href":"popFront.html","topicHref":"popFront.html"},{"name":"save","href":"save.html","topicHref":"save.html"},{"name":"empty","href":"empty.html","topicHref":"empty.html"},{"name":"captures","href":"captures.html","topicHref":"captures.html"},{"name":"opCast","href":"opCast.html","topicHref":"opCast.html"}],"pdf":false}
