
{"items":[{"name":"Old_Hungarian","href":"Old_Hungarian.html","topicHref":"Old_Hungarian.html"},{"name":"Coptic","href":"Coptic.html","topicHref":"Coptic.html"},{"name":"Ol_Chiki","href":"Ol_Chiki.html","topicHref":"Ol_Chiki.html"},{"name":"Cyrillic","href":"Cyrillic.html","topicHref":"Cyrillic.html"},{"name":"Thaana","href":"Thaana.html","topicHref":"Thaana.html"},{"name":"Inscriptional_Parthian","href":"Inscriptional_Parthian.html","topicHref":"Inscriptional_Parthian.html"},{"name":"Nabataean","href":"Nabataean.html","topicHref":"Nabataean.html"},{"name":"Ogham","href":"Ogham.html","topicHref":"Ogham.html"},{"name":"Meroitic_Hieroglyphs","href":"Meroitic_Hieroglyphs.html","topicHref":"Meroitic_Hieroglyphs.html"},{"name":"Makasar","href":"Makasar.html","topicHref":"Makasar.html"},{"name":"Siddham","href":"Siddham.html","topicHref":"Siddham.html"},{"name":"Old_Persian","href":"Old_Persian.html","topicHref":"Old_Persian.html"},{"name":"Imperial_Aramaic","href":"Imperial_Aramaic.html","topicHref":"Imperial_Aramaic.html"},{"name":"Myanmar","href":"Myanmar.html","topicHref":"Myanmar.html"},{"name":"Deseret","href":"Deseret.html","topicHref":"Deseret.html"},{"name":"Kaithi","href":"Kaithi.html","topicHref":"Kaithi.html"},{"name":"Medefaidrin","href":"Medefaidrin.html","topicHref":"Medefaidrin.html"},{"name":"Kayah_Li","href":"Kayah_Li.html","topicHref":"Kayah_Li.html"},{"name":"Hiragana","href":"Hiragana.html","topicHref":"Hiragana.html"},{"name":"Ahom","href":"Ahom.html","topicHref":"Ahom.html"},{"name":"Devanagari","href":"Devanagari.html","topicHref":"Devanagari.html"},{"name":"Tibetan","href":"Tibetan.html","topicHref":"Tibetan.html"},{"name":"Nko","href":"Nko.html","topicHref":"Nko.html"},{"name":"Brahmi","href":"Brahmi.html","topicHref":"Brahmi.html"},{"name":"Osage","href":"Osage.html","topicHref":"Osage.html"},{"name":"Nushu","href":"Nushu.html","topicHref":"Nushu.html"},{"name":"Cuneiform","href":"Cuneiform.html","topicHref":"Cuneiform.html"},{"name":"Takri","href":"Takri.html","topicHref":"Takri.html"},{"name":"Toto","href":"Toto.html","topicHref":"Toto.html"},{"name":"Latin","href":"Latin.html","topicHref":"Latin.html"},{"name":"Hanunoo","href":"Hanunoo.html","topicHref":"Hanunoo.html"},{"name":"Limbu","href":"Limbu.html","topicHref":"Limbu.html"},{"name":"Saurashtra","href":"Saurashtra.html","topicHref":"Saurashtra.html"},{"name":"Lisu","href":"Lisu.html","topicHref":"Lisu.html"},{"name":"Egyptian_Hieroglyphs","href":"Egyptian_Hieroglyphs.html","topicHref":"Egyptian_Hieroglyphs.html"},{"name":"Elbasan","href":"Elbasan.html","topicHref":"Elbasan.html"},{"name":"Palmyrene","href":"Palmyrene.html","topicHref":"Palmyrene.html"},{"name":"Tagbanwa","href":"Tagbanwa.html","topicHref":"Tagbanwa.html"},{"name":"Old_Italic","href":"Old_Italic.html","topicHref":"Old_Italic.html"},{"name":"Caucasian_Albanian","href":"Caucasian_Albanian.html","topicHref":"Caucasian_Albanian.html"},{"name":"Malayalam","href":"Malayalam.html","topicHref":"Malayalam.html"},{"name":"Inherited","href":"Inherited.html","topicHref":"Inherited.html"},{"name":"Sora_Sompeng","href":"Sora_Sompeng.html","topicHref":"Sora_Sompeng.html"},{"name":"Linear_B","href":"Linear_B.html","topicHref":"Linear_B.html"},{"name":"Nyiakeng_Puachue_Hmong","href":"Nyiakeng_Puachue_Hmong.html","topicHref":"Nyiakeng_Puachue_Hmong.html"},{"name":"Meroitic_Cursive","href":"Meroitic_Cursive.html","topicHref":"Meroitic_Cursive.html"},{"name":"Thai","href":"Thai.html","topicHref":"Thai.html"},{"name":"Mende_Kikakui","href":"Mende_Kikakui.html","topicHref":"Mende_Kikakui.html"},{"name":"Old_Sogdian","href":"Old_Sogdian.html","topicHref":"Old_Sogdian.html"},{"name":"Old_Turkic","href":"Old_Turkic.html","topicHref":"Old_Turkic.html"},{"name":"Samaritan","href":"Samaritan.html","topicHref":"Samaritan.html"},{"name":"Old_South_Arabian","href":"Old_South_Arabian.html","topicHref":"Old_South_Arabian.html"},{"name":"Hanifi_Rohingya","href":"Hanifi_Rohingya.html","topicHref":"Hanifi_Rohingya.html"},{"name":"Balinese","href":"Balinese.html","topicHref":"Balinese.html"},{"name":"Mandaic","href":"Mandaic.html","topicHref":"Mandaic.html"},{"name":"SignWriting","href":"SignWriting.html","topicHref":"SignWriting.html"},{"name":"Tifinagh","href":"Tifinagh.html","topicHref":"Tifinagh.html"},{"name":"Tai_Viet","href":"Tai_Viet.html","topicHref":"Tai_Viet.html"},{"name":"Syriac","href":"Syriac.html","topicHref":"Syriac.html"},{"name":"Soyombo","href":"Soyombo.html","topicHref":"Soyombo.html"},{"name":"Elymaic","href":"Elymaic.html","topicHref":"Elymaic.html"},{"name":"Hatran","href":"Hatran.html","topicHref":"Hatran.html"},{"name":"Chorasmian","href":"Chorasmian.html","topicHref":"Chorasmian.html"},{"name":"Glagolitic","href":"Glagolitic.html","topicHref":"Glagolitic.html"},{"name":"Osmanya","href":"Osmanya.html","topicHref":"Osmanya.html"},{"name":"Linear_A","href":"Linear_A.html","topicHref":"Linear_A.html"},{"name":"Mro","href":"Mro.html","topicHref":"Mro.html"},{"name":"Chakma","href":"Chakma.html","topicHref":"Chakma.html"},{"name":"Modi","href":"Modi.html","topicHref":"Modi.html"},{"name":"Bassa_Vah","href":"Bassa_Vah.html","topicHref":"Bassa_Vah.html"},{"name":"Han","href":"Han.html","topicHref":"Han.html"},{"name":"Multani","href":"Multani.html","topicHref":"Multani.html"},{"name":"Bopomofo","href":"Bopomofo.html","topicHref":"Bopomofo.html"},{"name":"Adlam","href":"Adlam.html","topicHref":"Adlam.html"},{"name":"Khitan_Small_Script","href":"Khitan_Small_Script.html","topicHref":"Khitan_Small_Script.html"},{"name":"Lao","href":"Lao.html","topicHref":"Lao.html"},{"name":"Psalter_Pahlavi","href":"Psalter_Pahlavi.html","topicHref":"Psalter_Pahlavi.html"},{"name":"Anatolian_Hieroglyphs","href":"Anatolian_Hieroglyphs.html","topicHref":"Anatolian_Hieroglyphs.html"},{"name":"Canadian_Aboriginal","href":"Canadian_Aboriginal.html","topicHref":"Canadian_Aboriginal.html"},{"name":"Common","href":"Common.html","topicHref":"Common.html"},{"name":"Gothic","href":"Gothic.html","topicHref":"Gothic.html"},{"name":"Yi","href":"Yi.html","topicHref":"Yi.html"},{"name":"Sinhala","href":"Sinhala.html","topicHref":"Sinhala.html"},{"name":"Rejang","href":"Rejang.html","topicHref":"Rejang.html"},{"name":"Lepcha","href":"Lepcha.html","topicHref":"Lepcha.html"},{"name":"Tai_Tham","href":"Tai_Tham.html","topicHref":"Tai_Tham.html"},{"name":"Dives_Akuru","href":"Dives_Akuru.html","topicHref":"Dives_Akuru.html"},{"name":"Meetei_Mayek","href":"Meetei_Mayek.html","topicHref":"Meetei_Mayek.html"},{"name":"Tirhuta","href":"Tirhuta.html","topicHref":"Tirhuta.html"},{"name":"Marchen","href":"Marchen.html","topicHref":"Marchen.html"},{"name":"Wancho","href":"Wancho.html","topicHref":"Wancho.html"},{"name":"Phoenician","href":"Phoenician.html","topicHref":"Phoenician.html"},{"name":"Gurmukhi","href":"Gurmukhi.html","topicHref":"Gurmukhi.html"},{"name":"Khudawadi","href":"Khudawadi.html","topicHref":"Khudawadi.html"},{"name":"Khojki","href":"Khojki.html","topicHref":"Khojki.html"},{"name":"Newa","href":"Newa.html","topicHref":"Newa.html"},{"name":"Dogra","href":"Dogra.html","topicHref":"Dogra.html"},{"name":"Oriya","href":"Oriya.html","topicHref":"Oriya.html"},{"name":"Tagalog","href":"Tagalog.html","topicHref":"Tagalog.html"},{"name":"Sundanese","href":"Sundanese.html","topicHref":"Sundanese.html"},{"name":"Old_Permic","href":"Old_Permic.html","topicHref":"Old_Permic.html"},{"name":"Shavian","href":"Shavian.html","topicHref":"Shavian.html"},{"name":"Lycian","href":"Lycian.html","topicHref":"Lycian.html"},{"name":"Miao","href":"Miao.html","topicHref":"Miao.html"},{"name":"Tangut","href":"Tangut.html","topicHref":"Tangut.html"},{"name":"Bengali","href":"Bengali.html","topicHref":"Bengali.html"},{"name":"Inscriptional_Pahlavi","href":"Inscriptional_Pahlavi.html","topicHref":"Inscriptional_Pahlavi.html"},{"name":"Vithkuqi","href":"Vithkuqi.html","topicHref":"Vithkuqi.html"},{"name":"Armenian","href":"Armenian.html","topicHref":"Armenian.html"},{"name":"New_Tai_Lue","href":"New_Tai_Lue.html","topicHref":"New_Tai_Lue.html"},{"name":"Sogdian","href":"Sogdian.html","topicHref":"Sogdian.html"},{"name":"Buhid","href":"Buhid.html","topicHref":"Buhid.html"},{"name":"Manichaean","href":"Manichaean.html","topicHref":"Manichaean.html"},{"name":"Greek","href":"Greek.html","topicHref":"Greek.html"},{"name":"Braille","href":"Braille.html","topicHref":"Braille.html"},{"name":"Avestan","href":"Avestan.html","topicHref":"Avestan.html"},{"name":"Arabic","href":"Arabic.html","topicHref":"Arabic.html"},{"name":"Javanese","href":"Javanese.html","topicHref":"Javanese.html"},{"name":"Lydian","href":"Lydian.html","topicHref":"Lydian.html"},{"name":"Pau_Cin_Hau","href":"Pau_Cin_Hau.html","topicHref":"Pau_Cin_Hau.html"},{"name":"Cypro_Minoan","href":"Cypro_Minoan.html","topicHref":"Cypro_Minoan.html"},{"name":"Buginese","href":"Buginese.html","topicHref":"Buginese.html"},{"name":"Batak","href":"Batak.html","topicHref":"Batak.html"},{"name":"Nandinagari","href":"Nandinagari.html","topicHref":"Nandinagari.html"},{"name":"Cham","href":"Cham.html","topicHref":"Cham.html"},{"name":"Gunjala_Gondi","href":"Gunjala_Gondi.html","topicHref":"Gunjala_Gondi.html"},{"name":"Cypriot","href":"Cypriot.html","topicHref":"Cypriot.html"},{"name":"Ugaritic","href":"Ugaritic.html","topicHref":"Ugaritic.html"},{"name":"Georgian","href":"Georgian.html","topicHref":"Georgian.html"},{"name":"Sharada","href":"Sharada.html","topicHref":"Sharada.html"},{"name":"Tamil","href":"Tamil.html","topicHref":"Tamil.html"},{"name":"Cherokee","href":"Cherokee.html","topicHref":"Cherokee.html"},{"name":"Pahawh_Hmong","href":"Pahawh_Hmong.html","topicHref":"Pahawh_Hmong.html"},{"name":"Syloti_Nagri","href":"Syloti_Nagri.html","topicHref":"Syloti_Nagri.html"},{"name":"Kharoshthi","href":"Kharoshthi.html","topicHref":"Kharoshthi.html"},{"name":"Zanabazar_Square","href":"Zanabazar_Square.html","topicHref":"Zanabazar_Square.html"},{"name":"Katakana","href":"Katakana.html","topicHref":"Katakana.html"},{"name":"Telugu","href":"Telugu.html","topicHref":"Telugu.html"},{"name":"Ethiopic","href":"Ethiopic.html","topicHref":"Ethiopic.html"},{"name":"Vai","href":"Vai.html","topicHref":"Vai.html"},{"name":"Bamum","href":"Bamum.html","topicHref":"Bamum.html"},{"name":"Hangul","href":"Hangul.html","topicHref":"Hangul.html"},{"name":"Mongolian","href":"Mongolian.html","topicHref":"Mongolian.html"},{"name":"Nag_Mundari","href":"Nag_Mundari.html","topicHref":"Nag_Mundari.html"},{"name":"Old_Uyghur","href":"Old_Uyghur.html","topicHref":"Old_Uyghur.html"},{"name":"Mahajani","href":"Mahajani.html","topicHref":"Mahajani.html"},{"name":"Khmer","href":"Khmer.html","topicHref":"Khmer.html"},{"name":"Grantha","href":"Grantha.html","topicHref":"Grantha.html"},{"name":"Kannada","href":"Kannada.html","topicHref":"Kannada.html"},{"name":"Kawi","href":"Kawi.html","topicHref":"Kawi.html"},{"name":"Yezidi","href":"Yezidi.html","topicHref":"Yezidi.html"},{"name":"Old_North_Arabian","href":"Old_North_Arabian.html","topicHref":"Old_North_Arabian.html"},{"name":"Tai_Le","href":"Tai_Le.html","topicHref":"Tai_Le.html"},{"name":"Hebrew","href":"Hebrew.html","topicHref":"Hebrew.html"},{"name":"Gujarati","href":"Gujarati.html","topicHref":"Gujarati.html"},{"name":"Tangsa","href":"Tangsa.html","topicHref":"Tangsa.html"},{"name":"Carian","href":"Carian.html","topicHref":"Carian.html"},{"name":"Bhaiksuki","href":"Bhaiksuki.html","topicHref":"Bhaiksuki.html"},{"name":"Masaram_Gondi","href":"Masaram_Gondi.html","topicHref":"Masaram_Gondi.html"},{"name":"Runic","href":"Runic.html","topicHref":"Runic.html"},{"name":"Duployan","href":"Duployan.html","topicHref":"Duployan.html"},{"name":"Warang_Citi","href":"Warang_Citi.html","topicHref":"Warang_Citi.html"},{"name":"Phags_Pa","href":"Phags_Pa.html","topicHref":"Phags_Pa.html"}],"pdf":false}
