
{"order":100,"items":[{"name":"Overview","href":"Overview.html","topicHref":"Overview.html"},{"name":"Classes","includedFrom":"~/phobos/std/sumtype/Classes/toc.yml","items":[{"name":"MatchException","href":"Classes/MatchException.html","topicHref":"Classes/MatchException.html"}]},{"name":"Structs","includedFrom":"~/phobos/std/sumtype/Structs/toc.yml","items":[{"name":"This","href":"Structs/This.html","topicHref":"Structs/This.html"},{"name":"SumType","href":"Structs/SumType.html","topicHref":"Structs/SumType.html"},{"name":"TagTuple","href":"Structs/TagTuple.html","topicHref":"Structs/TagTuple.html"}]},{"name":"Functions","includedFrom":"~/phobos/std/sumtype/Functions/toc.yml","items":[{"name":"isClose","href":"Functions/isClose.html","topicHref":"Functions/isClose.html"},{"name":"stride","href":"Functions/stride.html","topicHref":"Functions/stride.html"},{"name":"destroyIfOwner","href":"Functions/destroyIfOwner.html","topicHref":"Functions/destroyIfOwner.html"},{"name":"match","href":"Functions/match.html","topicHref":"Functions/match.html"},{"name":"tryMatch","href":"Functions/tryMatch.html","topicHref":"Functions/tryMatch.html"},{"name":"matchImpl","href":"Functions/matchImpl.html","topicHref":"Functions/matchImpl.html"}]}],"pdf":false}
