
{"items":[{"name":"initDriver","href":"initDriver.html","topicHref":"initDriver.html"},{"name":"uninitDriver","href":"uninitDriver.html","topicHref":"uninitDriver.html"},{"name":"processCompletions","href":"processCompletions.html","topicHref":"processCompletions.html"},{"name":"enter","href":"enter.html","topicHref":"enter.html"},{"name":"allocateNextSqe","href":"allocateNextSqe.html","topicHref":"allocateNextSqe.html"},{"name":"freeSqe","href":"freeSqe.html","topicHref":"freeSqe.html"},{"name":"enableFeatures","href":"enableFeatures.html","topicHref":"enableFeatures.html"}],"pdf":false}
