
{"items":[{"name":"lookaround","href":"lookaround.html","topicHref":"lookaround.html"},{"name":"restoreCode","href":"restoreCode.html","topicHref":"restoreCode.html"},{"name":"saveCode","href":"saveCode.html","topicHref":"saveCode.html"},{"name":"ctGenBlock","href":"ctGenBlock.html","topicHref":"ctGenBlock.html"},{"name":"ctGenGroup","href":"ctGenGroup.html","topicHref":"ctGenGroup.html"},{"name":"ctGenAlternation","href":"ctGenAlternation.html","topicHref":"ctGenAlternation.html"},{"name":"ctGenFixupCode","href":"ctGenFixupCode.html","topicHref":"ctGenFixupCode.html"},{"name":"ctQuickTest","href":"ctQuickTest.html","topicHref":"ctQuickTest.html"},{"name":"ctGenAtom","href":"ctGenAtom.html","topicHref":"ctGenAtom.html"},{"name":"ctAtomCode","href":"ctAtomCode.html","topicHref":"ctAtomCode.html"},{"name":"ctGenRegEx","href":"ctGenRegEx.html","topicHref":"ctGenRegEx.html"}],"pdf":false}
